multigtfs/__init__.py
multigtfs/admin.py
multigtfs/app_settings.py
multigtfs/compat.py
multigtfs/management/__init__.py
multigtfs/management/commands/__init__.py
multigtfs/management/commands/exportgtfs.py
multigtfs/management/commands/importgtfs.py
multigtfs/management/commands/refreshgeometries.py
multigtfs/migrations/0001_initial.py
multigtfs/migrations/0002_add_on_delete.py
multigtfs/migrations/0003_auto_20180826_2041.py
multigtfs/migrations/__init__.py
multigtfs/models/__init__.py
multigtfs/models/agency.py
multigtfs/models/base.py
multigtfs/models/block.py
multigtfs/models/fare.py
multigtfs/models/fare_rule.py
multigtfs/models/feed.py
multigtfs/models/feed_info.py
multigtfs/models/frequency.py
multigtfs/models/route.py
multigtfs/models/service.py
multigtfs/models/service_date.py
multigtfs/models/shape.py
multigtfs/models/stop.py
multigtfs/models/stop_time.py
multigtfs/models/transfer.py
multigtfs/models/trip.py
multigtfs/models/zone.py
multigtfs/models/fields/__init__.py
multigtfs/models/fields/seconds.py
multigtfs/tests/__init__.py
multigtfs/tests/test_agency.py
multigtfs/tests/test_block.py
multigtfs/tests/test_fare.py
multigtfs/tests/test_fare_rule.py
multigtfs/tests/test_feed.py
multigtfs/tests/test_feed_info.py
multigtfs/tests/test_fields.py
multigtfs/tests/test_frequency.py
multigtfs/tests/test_route.py
multigtfs/tests/test_service.py
multigtfs/tests/test_service_date.py
multigtfs/tests/test_shape.py
multigtfs/tests/test_stop.py
multigtfs/tests/test_stop_time.py
multigtfs/tests/test_transfer.py
multigtfs/tests/test_trip.py
multigtfs/tests/test_zone.py
multigtfs/tests/fixtures/README
multigtfs/tests/fixtures/test1.zip
multigtfs/tests/fixtures/test2.zip
multigtfs/tests/fixtures/test3.zip
multigtfs/tests/fixtures/test4.zip
multigtfs-1.1.2.dist-info/METADATA
multigtfs-1.1.2.dist-info/RECORD
multigtfs-1.1.2.dist-info/WHEEL
multigtfs-1.1.2.dist-info/top_level.txt
multigtfs-1.1.2.dist-info/zip-safe
